bitbucket_trello/__init__.py
bitbucket_trello/receiver.py
django_bitbucket_trello-0.0.6.dist-info/DESCRIPTION.rst
django_bitbucket_trello-0.0.6.dist-info/METADATA
django_bitbucket_trello-0.0.6.dist-info/RECORD
django_bitbucket_trello-0.0.6.dist-info/WHEEL
django_bitbucket_trello-0.0.6.dist-info/metadata.json
django_bitbucket_trello-0.0.6.dist-info/top_level.txt
