Metadata-Version: 2.0
Name: django-bitbucket-trello
Version: 0.0.6
Summary: Django Bitbucket & Trello Integration
Home-page: https://github.com/relique/django-bitbucket-trello
Author: Aldash Biibosunov
Author-email: pythonista8@gmail.com
License: MIT
Keywords: bitbucket trello integration django
Platform: UNKNOWN
Classifier: Development Status :: 3 - Alpha
Classifier: Environment :: Web Environment
Classifier: Framework :: Django
Classifier: Intended Audience :: Developers
Classifier: License :: OSI Approved :: MIT License
Classifier: Programming Language :: Python
Classifier: Programming Language :: Python :: 2
Classifier: Programming Language :: Python :: 3
Classifier: Topic :: Utilities
Requires-Dist: requests (>=2.11.1)
